Workbook

Sheet Executive_Dashboard
A1: PROJECT BHARAT-FLOW: ONDC RETAIL INVENTORY & CUSTOMER INTELLIGENCE
A2: Executive KPI Scorecard | Pan-India Multi-Echelon Retail Supply Chain (Oct 2025 – Sep 2026)
A3: NETWORK INVENTORY VALUE | C3: DELIVERED ANNUAL GMV | E3: ON-TIME SLA RATE | G3: ACTIVE BUYER BASE
A4: 60243136 | C4: 6115289.5 | E4: 0.81543155 | G4: 1056
A5: 595 SKU-Hub Positions | C5: 19,349 Line Items | E5: Target: >= 85.0% | G5: 83.8% Network Activation
A7: Table 1: Product Category Performance & Margin Architecture
A8: Category | B8: Active SKUs | C8: Units Sold | D8: Gross Revenue (₹) | E8: COGS (₹) | F8: Gross Profit (₹) | G8: Margin % | H8: Annual Turns
A9: Packaged Food & Staples | B9: 7 | C9: 9416 | D9: 1928327.5 | E9: 1668082 | F9: =D9-E9 -> 260245.54 | G9: =F9/D9 -> 0.1349592 | H9: =ROUND(E9/(SUMIF(Inventory_ABC_XYZ!$C$6:$C$40, A9, Inventory_ABC_XYZ!$F$6:$F$40)*0.18), 1) -> 5.6
A10: Personal & Home Care | B10: 7 | C10: 9235 | D10: 1588261.7 | E10: 1327933 | F10: =D10-E10 -> 260328.7 | G10: =F10/D10 -> 0.16390794 | H10: =ROUND(E10/(SUMIF(Inventory_ABC_XYZ!$C$6:$C$40, A10, Inventory_ABC_XYZ!$F$6:$F$40)*0.18), 1) -> 5.6
A11: Beverages & Snacks | B11: 7 | C11: 9902 | D11: 1345338.7 | E11: 1116848 | F11: =D11-E11 -> 228490.67 | G11: =F11/D11 -> 0.16983877 | H11: =ROUND(E11/(SUMIF(Inventory_ABC_XYZ!$C$6:$C$40, A11, Inventory_ABC_XYZ!$F$6:$F$40)*0.18), 1) -> 5.6
A12: Essential Pharma & OTC | B12: 7 | C12: 9736 | D12: 697413.47 | E12: 539734 | F12: =D12-E12 -> 157679.47 | G12: =F12/D12 -> 0.2260918 | H12: =ROUND(E12/(SUMIF(Inventory_ABC_XYZ!$C$6:$C$40, A12, Inventory_ABC_XYZ!$F$6:$F$40)*0.18), 1) -> 5.6
A13: Dairy & Perishables | B13: 7 | C13: 9361 | D13: 555948.16 | E13: 455684 | F13: =D13-E13 -> 100264.16 | G13: =F13/D13 -> 0.18034804 | H13: =ROUND(E13/(SUMIF(Inventory_ABC_XYZ!$C$6:$C$40, A13, Inventory_ABC_XYZ!$F$6:$F$40)*0.18), 1) -> 5.6
A14: Total / Network Weighted | B14: =SUM(B9:B13) -> 35 | C14: =SUM(C9:C13) -> 47650 | D14: =SUM(D9:D13) -> 6115289.5 | E14: =SUM(E9:E13) -> 5108281 | F14: =SUM(F9:F13) -> 1007008.5 | G14: =F14/D14 -> 0.16467062 | H14: =AVERAGE(H9:H13) -> 5.6
A16: Table 2: Geographic & City Tier Fulfillment Performance
A17: City Tier | B17: Registered Customers | C17: Active Customers | D17: Delivered Orders | E17: GMV (₹) | F17: AOV (₹) | G17: SLA Breach % | H17: Stockout %
A18: Tier-1 | B18: 322 | C18: 285 | D18: 4409 | E18: 1562666.8 | F18: =E18/D18 -> 354.42659 | G18: 0.1708 | H18: 0.0433
A19: Tier-2 | B19: 481 | C19: 416 | D19: 7327 | E19: 2714114.4 | F19: =E19/D19 -> 370.42643 | G19: 0.1897 | H19: 0.0401
A20: Tier-3 | B20: 397 | C20: 355 | D20: 5436 | E20: 1838508.3 | F20: =E20/D20 -> 338.20976 | G20: 0.1843 | H20: 0.07
A21: Total / Network | B21: =SUM(B18:B20) -> 1200 | C21: =SUM(C18:C20) -> 1056 | D21: =SUM(D18:D20) -> 17172 | E21: =SUM(E18:E20) -> 6115289.5 | F21: =E21/D21 -> 356.11982 | G21: =AVERAGE(G18:G20) -> 0.1816 | H21: =AVERAGE(H18:H20) -> 0.051133333

Sheet Inventory_ABC_XYZ
A1: SKU-LEVEL MULTI-DIMENSIONAL ABC-XYZ INVENTORY MATRIX & PRESCRIPTIVE OPTIMIZATION
A2: Pareto Value Classification (A/B/C) x Demand Predictability (X/Y/Z) | Dynamic ROP, EOQ, & Safety Stock
A3: Model Logic: ABC determined by Cumulative Consumption Value (80/15/5%). XYZ determined by Demand Coeff. of Variation (CV). ROP = (d*L) + SS. EOQ = sqrt(2*D*S/H).
A5: SKU ID | B5: Product Name | C5: Category | D5: Unit Cost (₹) | E5: Annual Demand (Units) | F5: Annual Consumption (₹) | G5: Cumul. Value % | H5: ABC Class | I5: Demand CV | J5: XYZ Class | K5: Safety Stock (Units) | L5: Reorder Point (ROP) | M5: EOQ (Units) | N5: Inventory Policy
A6: SKU-STP-001 | B6: Aashirvaad Shudh Chakki Atta 10kg | C6: Packaged Food & Staples | D6: 410 | E6: 1405 | F6: =D6*E6 -> 576050 | G6: =SUM($F$6:F6)/$F$41 -> 0.11276788 | H6: =IF(G6<=0.8, "A", IF(G6<=0.95, "B", "C")) -> A | I6: 0.209 | J6: =IF(I6<=0.45, "X", IF(I6<=0.85, "Y", "Z")) -> X | K6: 17 | L6: 32 | M6: =ROUND(SQRT((2*E6*250)/(D6*0.18)), 0) -> 98 | N6: =IF(H6="A", IF(J6="X", "JIT Automated Flow", "Continuous Buffer Review"), IF(H6="B", "Periodic Fixed Order", "Two-Bin Kanban")) -> JIT Automated Flow
A7: SKU-STP-004 | B7: India Gate Basmati Rice Rozzana 5kg | C7: Packaged Food & Staples | D7: 360 | E7: 1305 | F7: =D7*E7 -> 469800 | G7: =SUM($F$6:F7)/$F$41 -> 0.20473619 | H7: =IF(G7<=0.8, "A", IF(G7<=0.95, "B", "C")) -> A | I7: 0.218 | J7: =IF(I7<=0.45, "X", IF(I7<=0.85, "Y", "Z")) -> X | K7: 16 | L7: 30 | M7: =ROUND(SQRT((2*E7*220)/(D7*0.18)), 0) -> 94 | N7: =IF(H7="A", IF(J7="X", "JIT Automated Flow", "Continuous Buffer Review"), IF(H7="B", "Periodic Fixed Order", "Two-Bin Kanban")) -> JIT Automated Flow
A8: SKU-HPC-007 | B8: Head & Shoulders Anti-Dandruff Shampoo 340ml | C8: Personal & Home Care | D8: 240 | E8: 1407 | F8: =D8*E8 -> 337680 | G8: =SUM($F$6:F8)/$F$41 -> 0.27084062 | H8: =IF(G8<=0.8, "A", IF(G8<=0.95, "B", "C")) -> A | I8: 0.281 | J8: =IF(I8<=0.45, "X", IF(I8<=0.85, "Y", "Z")) -> X | K8: 18 | L8: 30 | M8: =ROUND(SQRT((2*E8*180)/(D8*0.18)), 0) -> 108 | N8: =IF(H8="A", IF(J8="X", "JIT Automated Flow", "Continuous Buffer Review"), IF(H8="B", "Periodic Fixed Order", "Two-Bin Kanban")) -> JIT Automated Flow
A9: SKU-SNK-001 | B9: Tata Tea Premium Desh Ki Chai 500g | C9: Beverages & Snacks | D9: 195 | E9: 1464 | F9: =D9*E9 -> 285480 | G9: =SUM($F$6:F9)/$F$41 -> 0.32672635 | H9: =IF(G9<=0.8, "A", IF(G9<=0.95, "B", "C")) -> A | I9: 0.229 | J9: =IF(I9<=0.45, "X", IF(I9<=0.85, "Y", "Z")) -> X | K9: 18 | L9: 34 | M9: =ROUND(SQRT((2*E9*170)/(D9*0.16)), 0) -> 126 | N9: =IF(H9="A", IF(J9="X", "JIT Automated Flow", "Continuous Buffer Review"), IF(H9="B", "Periodic Fixed Order", "Two-Bin Kanban")) -> JIT Automated Flow
A10: SKU-SNK-007 | B10: Cadbury Bournvita Chocolate Health Drink 500g | C10: Beverages & Snacks | D10: 195 | E10: 1318 | F10: =D10*E10 -> 257010 | G10: =SUM($F$6:F10)/$F$41 -> 0.37703877 | H10: =IF(G10<=0.8, "A", IF(G10<=0.95, "B", "C")) -> A | I10: 0.278 | J10: =IF(I10<=0.45, "X", IF(I10<=0.85, "Y", "Z")) -> X | K10: 20 | L10: 34 | M10: =ROUND(SQRT((2*E10*170)/(D10*0.16)), 0) -> 120 | N10: =IF(H10="A", IF(J10="X", "JIT Automated Flow", "Continuous Buffer Review"), IF(H10="B", "Periodic Fixed Order", "Two-Bin Kanban")) -> JIT Automated Flow
A11: SKU-HPC-006 | B11: Lizol Disinfectant Floor Cleaner Citrus 1L | C11: Personal & Home Care | D11: 168 | E11: 1397 | F11: =D11*E11 -> 234696 | G11: =SUM($F$6:F11)/$F$41 -> 0.422983 | H11: =IF(G11<=0.8, "A", IF(G11<=0.95, "B", "C")) -> A | I11: 0.395 | J11: =IF(I11<=0.45, "X", IF(I11<=0.85, "Y", "Z")) -> X | K11: 24 | L11: 35 | M11: =ROUND(SQRT((2*E11*170)/(D11*0.16)), 0) -> 133 | N11: =IF(H11="A", IF(J11="X", "JIT Automated Flow", "Continuous Buffer Review"), IF(H11="B", "Periodic Fixed Order", "Two-Bin Kanban")) -> JIT Automated Flow
A12: SKU-HPC-005 | B12: Parachute 100% Pure Coconut Oil 500ml | C12: Personal & Home Care | D12: 155 | E12: 1375 | F12: =D12*E12 -> 213125 | G12: =SUM($F$6:F12)/$F$41 -> 0.46470447 | H12: =IF(G12<=0.8, "A", IF(G12<=0.95, "B", "C")) -> A | I12: 0.341 | J12: =IF(I12<=0.45, "X", IF(I12<=0.85, "Y", "Z")) -> X | K12: 28 | L12: 47 | M12: =ROUND(SQRT((2*E12*160)/(D12*0.16)), 0) -> 133 | N12: =IF(H12="A", IF(J12="X", "JIT Automated Flow", "Continuous Buffer Review"), IF(H12="B", "Periodic Fixed Order", "Two-Bin Kanban")) -> JIT Automated Flow
A13: SKU-STP-007 | B13: Organic Tattva Unpolished Toor Dal 1kg | C13: Packaged Food & Staples | D13: 145 | E13: 1442 | F13: =D13*E13 -> 209090 | G13: =SUM($F$6:F13)/$F$41 -> 0.50563604 | H13: =IF(G13<=0.8, "A", IF(G13<=0.95, "B", "C")) -> A | I13: 0.19 | J13: =IF(I13<=0.45, "X", IF(I13<=0.85, "Y", "Z")) -> X | K13: 16 | L13: 32 | M13: =ROUND(SQRT((2*E13*150)/(D13*0.18)), 0) -> 129 | N13: =IF(H13="A", IF(J13="X", "JIT Automated Flow", "Continuous Buffer Review"), IF(H13="B", "Periodic Fixed Order", "Two-Bin Kanban")) -> JIT Automated Flow
A14: SKU-SNK-002 | B14: Nescafe Classic 100% Pure Instant Coffee 50g | C14: Beverages & Snacks | D14: 145 | E14: 1438 | F14: =D14*E14 -> 208510 | G14: =SUM($F$6:F14)/$F$41 -> 0.54645408 | H14: =IF(G14<=0.8, "A", IF(G14<=0.95, "B", "C")) -> A | I14: 0.265 | J14: =IF(I14<=0.45, "X", IF(I14<=0.85, "Y", "Z")) -> X | K14: 21 | L14: 37 | M14: =ROUND(SQRT((2*E14*150)/(D14*0.18)), 0) -> 129 | N14: =IF(H14="A", IF(J14="X", "JIT Automated Flow", "Continuous Buffer Review"), IF(H14="B", "Periodic Fixed Order", "Two-Bin Kanban")) -> JIT Automated Flow
A15: SKU-PHM-005 | B15: Dettol Antiseptic Liquid 250ml | C15: Essential Pharma & OTC | D15: 120 | E15: 1659 | F15: =D15*E15 -> 199080 | G15: =SUM($F$6:F15)/$F$41 -> 0.5854261 | H15: =IF(G15<=0.8, "A", IF(G15<=0.95, "B", "C")) -> A | I15: 0.343 | J15: =IF(I15<=0.45, "X", IF(I15<=0.85, "Y", "Z")) -> X | K15: 25 | L15: 39 | M15: =ROUND(SQRT((2*E15*130)/(D15*0.18)), 0) -> 141 | N15: =IF(H15="A", IF(J15="X", "JIT Automated Flow", "Continuous Buffer Review"), IF(H15="B", "Periodic Fixed Order", "Two-Bin Kanban")) -> JIT Automated Flow
A16: SKU-STP-002 | B16: Fortune Sunlite Refined Sunflower Oil 1L | C16: Packaged Food & Staples | D16: 125 | E16: 1360 | F16: =D16*E16 -> 170000 | G16: =SUM($F$6:F16)/$F$41 -> 0.61870539 | H16: =IF(G16<=0.8, "A", IF(G16<=0.95, "B", "C")) -> A | I16: 0.291 | J16: =IF(I16<=0.45, "X", IF(I16<=0.85, "Y", "Z")) -> X | K16: 24 | L16: 43 | M16: =ROUND(SQRT((2*E16*180)/(D16*0.18)), 0) -> 148 | N16: =IF(H16="A", IF(J16="X", "JIT Automated Flow", "Continuous Buffer Review"), IF(H16="B", "Periodic Fixed Order", "Two-Bin Kanban")) -> JIT Automated Flow
A17: SKU-PHM-006 | B17: PMBJP Digital Flexible Thermometer | C17: Essential Pharma & OTC | D17: 95 | E17: 1396 | F17: =D17*E17 -> 132620 | G17: =SUM($F$6:F17)/$F$41 -> 0.64466716 | H17: =IF(G17<=0.8, "A", IF(G17<=0.95, "B", "C")) -> A | I17: 0.226 | J17: =IF(I17<=0.45, "X", IF(I17<=0.85, "Y", "Z")) -> X | K17: 26 | L17: 53 | M17: =ROUND(SQRT((2*E17*160)/(D17*0.2)), 0) -> 153 | N17: =IF(H17="A", IF(J17="X", "JIT Automated Flow", "Continuous Buffer Review"), IF(H17="B", "Periodic Fixed Order", "Two-Bin Kanban")) -> JIT Automated Flow
A18: SKU-PHM-007 | B18: Volini Joint & Muscle Pain Relief Gel 50g | C18: Essential Pharma & OTC | D18: 115 | E18: 1398 | F18: =D18*E18 -> 160770 | G18: =SUM($F$6:F18)/$F$41 -> 0.67613959 | H18: =IF(G18<=0.8, "A", IF(G18<=0.95, "B", "C")) -> A | I18: 0.321 | J18: =IF(I18<=0.45, "X", IF(I18<=0.85, "Y", "Z")) -> X | K18: 30 | L18: 53 | M18: =ROUND(SQRT((2*E18*120)/(D18*0.2)), 0) -> 121 | N18: =IF(H18="A", IF(J18="X", "JIT Automated Flow", "Continuous Buffer Review"), IF(H18="B", "Periodic Fixed Order", "Two-Bin Kanban")) -> JIT Automated Flow
A19: SKU-STP-006 | B19: Catch Turmeric Powder 500g | C19: Packaged Food & Staples | D19: 110 | E19: 1380 | F19: =D19*E19 -> 151800 | G19: =SUM($F$6:F19)/$F$41 -> 0.70585604 | H19: =IF(G19<=0.8, "A", IF(G19<=0.95, "B", "C")) -> A | I19: 0.245 | J19: =IF(I19<=0.45, "X", IF(I19<=0.85, "Y", "Z")) -> X | K19: 21 | L19: 40 | M19: =ROUND(SQRT((2*E19*110)/(D19*0.16)), 0) -> 131 | N19: =IF(H19="A", IF(J19="X", "JIT Automated Flow", "Continuous Buffer Review"), IF(H19="B", "Periodic Fixed Order", "Two-Bin Kanban")) -> JIT Automated Flow
A20: SKU-HPC-001 | B20: Surf Excel Easy Wash Detergent Powder 1kg | C20: Personal & Home Care | D20: 118 | E20: 1351 | F20: =D20*E20 -> 159418 | G20: =SUM($F$6:F20)/$F$41 -> 0.7370638 | H20: =IF(G20<=0.8, "A", IF(G20<=0.95, "B", "C")) -> A | I20: 0.229 | J20: =IF(I20<=0.45, "X", IF(I20<=0.85, "Y", "Z")) -> X | K20: 14 | L20: 25 | M20: =ROUND(SQRT((2*E20*180)/(D20*0.16)), 0) -> 161 | N20: =IF(H20="A", IF(J20="X", "JIT Automated Flow", "Continuous Buffer Review"), IF(H20="B", "Periodic Fixed Order", "Two-Bin Kanban")) -> JIT Automated Flow
A21: SKU-SNK-003 | B21: Haldirams Nagpur Aloo Bhujia Namkeen 400g | C21: Beverages & Snacks | D21: 92 | E21: 1573 | F21: =D21*E21 -> 144716 | G21: =SUM($F$6:F21)/$F$41 -> 0.76539349 | H21: =IF(G21<=0.8, "A", IF(G21<=0.95, "B", "C")) -> A | I21: 0.294 | J21: =IF(I21<=0.45, "X", IF(I21<=0.85, "Y", "Z")) -> X | K21: 24 | L21: 41 | M21: =ROUND(SQRT((2*E21*140)/(D21*0.18)), 0) -> 163 | N21: =IF(H21="A", IF(J21="X", "JIT Automated Flow", "Continuous Buffer Review"), IF(H21="B", "Periodic Fixed Order", "Two-Bin Kanban")) -> JIT Automated Flow
A22: SKU-HPC-004 | B22: Dabur Red Ayurvedic Toothpaste 300g | C22: Personal & Home Care | D22: 112 | E22: 1295 | F22: =D22*E22 -> 145040 | G22: =SUM($F$6:F22)/$F$41 -> 0.7937866 | H22: =IF(G22<=0.8, "A", IF(G22<=0.95, "B", "C")) -> A | I22: 0.267 | J22: =IF(I22<=0.45, "X", IF(I22<=0.85, "Y", "Z")) -> X | K22: 21 | L22: 39 | M22: =ROUND(SQRT((2*E22*130)/(D22*0.17)), 0) -> 133 | N22: =IF(H22="A", IF(J22="X", "JIT Automated Flow", "Continuous Buffer Review"), IF(H22="B", "Periodic Fixed Order", "Two-Bin Kanban")) -> JIT Automated Flow
A23: SKU-SNK-005 | B23: Real Fruit Power Mixed Fruit Juice 1L | C23: Beverages & Snacks | D23: 98 | E23: 1372 | F23: =D23*E23 -> 134456 | G23: =SUM($F$6:F23)/$F$41 -> 0.82010778 | H23: =IF(G23<=0.8, "A", IF(G23<=0.95, "B", "C")) -> B | I23: 0.253 | J23: =IF(I23<=0.45, "X", IF(I23<=0.85, "Y", "Z")) -> X | K23: 22 | L23: 41 | M23: =ROUND(SQRT((2*E23*150)/(D23*0.2)), 0) -> 145 | N23: =IF(H23="A", IF(J23="X", "JIT Automated Flow", "Continuous Buffer Review"), IF(H23="B", "Periodic Fixed Order", "Two-Bin Kanban")) -> Periodic Fixed Order
A24: SKU-HPC-003 | B24: Lifebuoy Total Germ Protection Soap 125g (Pack of 4) | C24: Personal & Home Care | D24: 110 | E24: 1177 | F24: =D24*E24 -> 129470 | G24: =SUM($F$6:F24)/$F$41 -> 0.8454529 | H24: =IF(G24<=0.8, "A", IF(G24<=0.95, "B", "C")) -> B | I24: 0.308 | J24: =IF(I24<=0.45, "X", IF(I24<=0.85, "Y", "Z")) -> X | K24: 16 | L24: 26 | M24: =ROUND(SQRT((2*E24*150)/(D24*0.16)), 0) -> 142 | N24: =IF(H24="A", IF(J24="X", "JIT Automated Flow", "Continuous Buffer Review"), IF(H24="B", "Periodic Fixed Order", "Two-Bin Kanban")) -> Periodic Fixed Order
A25: SKU-PER-002 | B25: Mother Dairy Classic Malai Paneer 200g | C25: Dairy & Perishables | D25: 82 | E25: 1468 | F25: =D25*E25 -> 120376 | G25: =SUM($F$6:F25)/$F$41 -> 0.86901778 | H25: =IF(G25<=0.8, "A", IF(G25<=0.95, "B", "C")) -> B | I25: 0.27 | J25: =IF(I25<=0.45, "X", IF(I25<=0.85, "Y", "Z")) -> X | K25: 15 | L25: 23 | M25: =ROUND(SQRT((2*E25*110)/(D25*0.28)), 0) -> 119 | N25: =IF(H25="A", IF(J25="X", "JIT Automated Flow", "Continuous Buffer Review"), IF(H25="B", "Periodic Fixed Order", "Two-Bin Kanban")) -> Periodic Fixed Order
A26: SKU-HPC-002 | B26: Vim Dishwash Gel Lemon 500ml | C26: Personal & Home Care | D26: 88 | E26: 1233 | F26: =D26*E26 -> 108504 | G26: =SUM($F$6:F26)/$F$41 -> 0.89025858 | H26: =IF(G26<=0.8, "A", IF(G26<=0.95, "B", "C")) -> B | I26: 0.25 | J26: =IF(I26<=0.45, "X", IF(I26<=0.85, "Y", "Z")) -> X | K26: 14 | L26: 24 | M26: =ROUND(SQRT((2*E26*140)/(D26*0.16)), 0) -> 157 | N26: =IF(H26="A", IF(J26="X", "JIT Automated Flow", "Continuous Buffer Review"), IF(H26="B", "Periodic Fixed Order", "Two-Bin Kanban")) -> Periodic Fixed Order
A27: SKU-PER-006 | B27: Fresh Nashik Grade-A Red Onions 2kg | C27: Dairy & Perishables | D27: 52 | E27: 1360 | F27: =D27*E27 -> 70720 | G27: =SUM($F$6:F27)/$F$41 -> 0.90410277 | H27: =IF(G27<=0.8, "A", IF(G27<=0.95, "B", "C")) -> B | I27: 0.348 | J27: =IF(I27<=0.45, "X", IF(I27<=0.85, "Y", "Z")) -> X | K27: 17 | L27: 24 | M27: =ROUND(SQRT((2*E27*100)/(D27*0.32)), 0) -> 128 | N27: =IF(H27="A", IF(J27="X", "JIT Automated Flow", "Continuous Buffer Review"), IF(H27="B", "Periodic Fixed Order", "Two-Bin Kanban")) -> Periodic Fixed Order
A28: SKU-PER-001 | B28: Amul Taaza Homogenised Toned Milk 1L Tetra | C28: Dairy & Perishables | D28: 60 | E28: 1312 | F28: =D28*E28 -> 78720 | G28: =SUM($F$6:F28)/$F$41 -> 0.91951304 | H28: =IF(G28<=0.8, "A", IF(G28<=0.95, "B", "C")) -> B | I28: 0.199 | J28: =IF(I28<=0.45, "X", IF(I28<=0.85, "Y", "Z")) -> X | K28: 10 | L28: 17 | M28: =ROUND(SQRT((2*E28*120)/(D28*0.25)), 0) -> 145 | N28: =IF(H28="A", IF(J28="X", "JIT Automated Flow", "Continuous Buffer Review"), IF(H28="B", "Periodic Fixed Order", "Two-Bin Kanban")) -> Periodic Fixed Order
A29: SKU-STP-005 | B29: Maggi 2-Minute Masala Noodles 280g (Pack of 4) | C29: Packaged Food & Staples | D29: 50 | E29: 1322 | F29: =D29*E29 -> 66100 | G29: =SUM($F$6:F29)/$F$41 -> 0.93245282 | H29: =IF(G29<=0.8, "A", IF(G29<=0.95, "B", "C")) -> B | I29: 0.252 | J29: =IF(I29<=0.45, "X", IF(I29<=0.85, "Y", "Z")) -> X | K29: 18 | L29: 32 | M29: =ROUND(SQRT((2*E29*140)/(D29*0.18)), 0) -> 203 | N29: =IF(H29="A", IF(J29="X", "JIT Automated Flow", "Continuous Buffer Review"), IF(H29="B", "Periodic Fixed Order", "Two-Bin Kanban")) -> Periodic Fixed Order
A30: SKU-PER-007 | B30: Farm Fresh Pahadi Potatoes 2kg Net Bag | C30: Dairy & Perishables | D30: 44 | E30: 1255 | F30: =D30*E30 -> 55220 | G30: =SUM($F$6:F30)/$F$41 -> 0.94326271 | H30: =IF(G30<=0.8, "A", IF(G30<=0.95, "B", "C")) -> B | I30: 0.233 | J30: =IF(I30<=0.45, "X", IF(I30<=0.85, "Y", "Z")) -> X | K30: 11 | L30: 18 | M30: =ROUND(SQRT((2*E30*90)/(D30*0.3)), 0) -> 131 | N30: =IF(H30="A", IF(J30="X", "JIT Automated Flow", "Continuous Buffer Review"), IF(H30="B", "Periodic Fixed Order", "Two-Bin Kanban")) -> Periodic Fixed Order
A31: SKU-PER-004 | B31: Epigamia Natural Greek Yogurt 90g Cup | C31: Dairy & Perishables | D31: 42 | E31: 1400 | F31: =D31*E31 -> 58800 | G31: =SUM($F$6:F31)/$F$41 -> 0.95477344 | H31: =IF(G31<=0.8, "A", IF(G31<=0.95, "B", "C")) -> C | I31: 0.273 | J31: =IF(I31<=0.45, "X", IF(I31<=0.85, "Y", "Z")) -> X | K31: 14 | L31: 22 | M31: =ROUND(SQRT((2*E31*120)/(D31*0.3)), 0) -> 163 | N31: =IF(H31="A", IF(J31="X", "JIT Automated Flow", "Continuous Buffer Review"), IF(H31="B", "Periodic Fixed Order", "Two-Bin Kanban")) -> Two-Bin Kanban
A32: SKU-SNK-004 | B32: Britannia Good Day Butter Cookies 200g | C32: Beverages & Snacks | D32: 36 | E32: 1255 | F32: =D32*E32 -> 45180 | G32: =SUM($F$6:F32)/$F$41 -> 0.9636179 | H32: =IF(G32<=0.8, "A", IF(G32<=0.95, "B", "C")) -> C | I32: 0.254 | J32: =IF(I32<=0.45, "X", IF(I32<=0.85, "Y", "Z")) -> X | K32: 15 | L32: 25 | M32: =ROUND(SQRT((2*E32*110)/(D32*0.18)), 0) -> 206 | N32: =IF(H32="A", IF(J32="X", "JIT Automated Flow", "Continuous Buffer Review"), IF(H32="B", "Periodic Fixed Order", "Two-Bin Kanban")) -> Two-Bin Kanban
A33: SKU-SNK-006 | B33: Paper Boat Aamras Alphonso Mango 250ml | C33: Beverages & Snacks | D33: 28 | E33: 1482 | F33: =D33*E33 -> 41496 | G33: =SUM($F$6:F33)/$F$41 -> 0.97174118 | H33: =IF(G33<=0.8, "A", IF(G33<=0.95, "B", "C")) -> C | I33: 0.214 | J33: =IF(I33<=0.45, "X", IF(I33<=0.85, "Y", "Z")) -> X | K33: 18 | L33: 34 | M33: =ROUND(SQRT((2*E33*120)/(D33*0.2)), 0) -> 252 | N33: =IF(H33="A", IF(J33="X", "JIT Automated Flow", "Continuous Buffer Review"), IF(H33="B", "Periodic Fixed Order", "Two-Bin Kanban")) -> Two-Bin Kanban
A34: SKU-PER-005 | B34: Farm Fresh Hybrid Salad Tomatoes 1kg | C34: Dairy & Perishables | D34: 28 | E34: 1240 | F34: =D34*E34 -> 34720 | G34: =SUM($F$6:F34)/$F$41 -> 0.97853799 | H34: =IF(G34<=0.8, "A", IF(G34<=0.95, "B", "C")) -> C | I34: 0.224 | J34: =IF(I34<=0.45, "X", IF(I34<=0.85, "Y", "Z")) -> X | K34: 10 | L34: 17 | M34: =ROUND(SQRT((2*E34*90)/(D34*0.35)), 0) -> 151 | N34: =IF(H34="A", IF(J34="X", "JIT Automated Flow", "Continuous Buffer Review"), IF(H34="B", "Periodic Fixed Order", "Two-Bin Kanban")) -> Two-Bin Kanban
A35: SKU-PER-003 | B35: Nandini Fresh Thick Curd 500g Pouch | C35: Dairy & Perishables | D35: 28 | E35: 1326 | F35: =D35*E35 -> 37128 | G35: =SUM($F$6:F35)/$F$41 -> 0.98580618 | H35: =IF(G35<=0.8, "A", IF(G35<=0.95, "B", "C")) -> C | I35: 0.319 | J35: =IF(I35<=0.45, "X", IF(I35<=0.85, "Y", "Z")) -> X | K35: 15 | L35: 22 | M35: =ROUND(SQRT((2*E35*100)/(D35*0.28)), 0) -> 184 | N35: =IF(H35="A", IF(J35="X", "JIT Automated Flow", "Continuous Buffer Review"), IF(H35="B", "Periodic Fixed Order", "Two-Bin Kanban")) -> Two-Bin Kanban
A36: SKU-STP-003 | B36: Tata Salt Vacuum Evaporated Iodized 1kg | C36: Packaged Food & Staples | D36: 21 | E36: 1202 | F36: =D36*E36 -> 25242 | G36: =SUM($F$6:F36)/$F$41 -> 0.99074757 | H36: =IF(G36<=0.8, "A", IF(G36<=0.95, "B", "C")) -> C | I36: 0.278 | J36: =IF(I36<=0.45, "X", IF(I36<=0.85, "Y", "Z")) -> X | K36: 18 | L36: 31 | M36: =ROUND(SQRT((2*E36*120)/(D36*0.15)), 0) -> 303 | N36: =IF(H36="A", IF(J36="X", "JIT Automated Flow", "Continuous Buffer Review"), IF(H36="B", "Periodic Fixed Order", "Two-Bin Kanban")) -> Two-Bin Kanban
A37: SKU-PHM-003 | B37: Electral WHO-Formula ORS Powder 21.8g Sachet | C37: Essential Pharma & OTC | D37: 16 | E37: 1437 | F37: =D37*E37 -> 22992 | G37: =SUM($F$6:F37)/$F$41 -> 0.9952485 | H37: =IF(G37<=0.8, "A", IF(G37<=0.95, "B", "C")) -> C | I37: 0.246 | J37: =IF(I37<=0.45, "X", IF(I37<=0.85, "Y", "Z")) -> X | K37: 25 | L37: 49 | M37: =ROUND(SQRT((2*E37*80)/(D37*0.2)), 0) -> 268 | N37: =IF(H37="A", IF(J37="X", "JIT Automated Flow", "Continuous Buffer Review"), IF(H37="B", "Periodic Fixed Order", "Two-Bin Kanban")) -> Two-Bin Kanban
A38: SKU-PHM-002 | B38: PMBJP Jan Aushadhi Metformin 500mg (10 Tabs) | C38: Essential Pharma & OTC | D38: 8 | E38: 1326 | F38: =D38*E38 -> 10608 | G38: =SUM($F$6:F38)/$F$41 -> 0.99732513 | H38: =IF(G38<=0.8, "A", IF(G38<=0.95, "B", "C")) -> C | I38: 0.337 | J38: =IF(I38<=0.45, "X", IF(I38<=0.85, "Y", "Z")) -> X | K38: 33 | L38: 58 | M38: =ROUND(SQRT((2*E38*95)/(D38*0.22)), 0) -> 378 | N38: =IF(H38="A", IF(J38="X", "JIT Automated Flow", "Continuous Buffer Review"), IF(H38="B", "Periodic Fixed Order", "Two-Bin Kanban")) -> Two-Bin Kanban
A39: SKU-PHM-001 | B39: PMBJP Jan Aushadhi Paracetamol 650mg (10 Tabs) | C39: Essential Pharma & OTC | D39: 6.5 | E39: 1162 | F39: =D39*E39 -> 7553 | G39: =SUM($F$6:F39)/$F$41 -> 0.99880371 | H39: =IF(G39<=0.8, "A", IF(G39<=0.95, "B", "C")) -> C | I39: 0.275 | J39: =IF(I39<=0.45, "X", IF(I39<=0.85, "Y", "Z")) -> X | K39: 25 | L39: 47 | M39: =ROUND(SQRT((2*E39*90)/(D39*0.22)), 0) -> 382 | N39: =IF(H39="A", IF(J39="X", "JIT Automated Flow", "Continuous Buffer Review"), IF(H39="B", "Periodic Fixed Order", "Two-Bin Kanban")) -> Two-Bin Kanban
A40: SKU-PHM-004 | B40: PMBJP Jan Aushadhi Cetirizine 10mg (10 Tabs) | C40: Essential Pharma & OTC | D40: 4.5 | E40: 1358 | F40: =D40*E40 -> 6111 | G40: =SUM($F$6:F40)/$F$41 -> 1 | H40: =IF(G40<=0.8, "A", IF(G40<=0.95, "B", "C")) -> C | I40: 0.177 | J40: =IF(I40<=0.45, "X", IF(I40<=0.85, "Y", "Z")) -> X | K40: 22 | L40: 48 | M40: =ROUND(SQRT((2*E40*85)/(D40*0.22)), 0) -> 483 | N40: =IF(H40="A", IF(J40="X", "JIT Automated Flow", "Continuous Buffer Review"), IF(H40="B", "Periodic Fixed Order", "Two-Bin Kanban")) -> Two-Bin Kanban
A41: Total / Network Portfolio | D41: =AVERAGE(D6:D40) -> 105.77143 | E41: =SUM(E6:E40) -> 47650 | F41: =SUM(F6:F40) -> 5108281 | G41: 1 | I41: =AVERAGE(I6:I40) -> 0.26662857 | K41: =SUM(K6:K40) -> 681 | L41: =SUM(L6:L40) -> 1202 | M41: =AVERAGE(M6:M40) -> 176.02857

Sheet Customer_RFM_Analysis
A1: CUSTOMER RFM SEGMENTATION & PREDICTIVE LIFETIME VALUE (CLV) MODEL
A2: Recency (Days to 2026-09-30) | Frequency (Delivered Orders) | Monetary Spend (₹) | Targeted Retention Action
A3: Cohort Segmentation: Champions (R>=4, F>=4, M>=4), Loyalists (R>=3, F>=3), Potential Loyalists (R>=3, F<3), At Risk (R=2, F>=3), Hibernating (R<=2, F<=2).
A5: Customer ID | B5: Customer Name | C5: City | D5: Tier | E5: Customer Type | F5: Recency (Days) | G5: Frequency (Orders) | H5: Monetary Spend (₹) | I5: AOV (₹) | J5: RFM Segment | K5: Prescriptive Action
A6: CUST-0935 | B6: Krishna Singh | C6: Patna | D6: Tier-2 | E6: Micro-Enterprise / Kirana Reseller | F6: 9 | G6: 21 | H6: 98564.2 | I6: =H6/G6 -> 4693.5333 | J6: Champions | K6: VIP Fast-Track SLA & Exclusive Pre-Booking
A7: CUST-0216 | B7: Kavita Deshmukh | C7: Bengaluru | D7: Tier-1 | E7: Micro-Enterprise / Kirana Reseller | F7: 23 | G7: 23 | H7: 95732.44 | I7: =H7/G7 -> 4162.28 | J7: Champions | K7: VIP Fast-Track SLA & Exclusive Pre-Booking
A8: CUST-1147 | B8: Reyansh Garg | C8: Bhopal | D8: Tier-2 | E8: Micro-Enterprise / Kirana Reseller | F8: 11 | G8: 25 | H8: 95676.78 | I8: =H8/G8 -> 3827.0712 | J8: Champions | K8: VIP Fast-Track SLA & Exclusive Pre-Booking
A9: CUST-0714 | B9: Rohan Menon | C9: Lucknow | D9: Tier-2 | E9: Micro-Enterprise / Kirana Reseller | F9: 8 | G9: 23 | H9: 84562.26 | I9: =H9/G9 -> 3676.62 | J9: Champions | K9: VIP Fast-Track SLA & Exclusive Pre-Booking
A10: CUST-1035 | B10: Krishna Deshmukh | C10: New Delhi | D10: Tier-1 | E10: Micro-Enterprise / Kirana Reseller | F10: 4 | G10: 23 | H10: 83682.74 | I10: =H10/G10 -> 3638.38 | J10: Champions | K10: VIP Fast-Track SLA & Exclusive Pre-Booking
A11: CUST-0830 | B11: Aditya Gupta | C11: Patna | D11: Tier-2 | E11: Micro-Enterprise / Kirana Reseller | F11: 13 | G11: 22 | H11: 82452.24 | I11: =H11/G11 -> 3747.8291 | J11: Champions | K11: VIP Fast-Track SLA & Exclusive Pre-Booking
A12: CUST-0485 | B12: Deepak Garg | C12: Warangal | D12: Tier-3 | E12: Micro-Enterprise / Kirana Reseller | F12: 20 | G12: 18 | H12: 76815.86 | I12: =H12/G12 -> 4267.5478 | J12: Champions | K12: VIP Fast-Track SLA & Exclusive Pre-Booking
A13: CUST-1165 | B13: Vivaan Das | C13: Jammu | D13: Tier-3 | E13: Micro-Enterprise / Kirana Reseller | F13: 8 | G13: 19 | H13: 71375.44 | I13: =H13/G13 -> 3756.6021 | J13: Champions | K13: VIP Fast-Track SLA & Exclusive Pre-Booking
A14: CUST-0920 | B14: Saanvi Banerjee | C14: Guwahati | D14: Tier-2 | E14: Micro-Enterprise / Kirana Reseller | F14: 2 | G14: 24 | H14: 71092.54 | I14: =H14/G14 -> 2962.1892 | J14: Champions | K14: VIP Fast-Track SLA & Exclusive Pre-Booking
A15: CUST-0270 | B15: Ishaan Garg | C15: Lucknow | D15: Tier-2 | E15: Micro-Enterprise / Kirana Reseller | F15: 13 | G15: 17 | H15: 66041.74 | I15: =H15/G15 -> 3884.8082 | J15: Champions | K15: VIP Fast-Track SLA & Exclusive Pre-Booking
A16: CUST-0241 | B16: Riya Patil | C16: Guwahati | D16: Tier-2 | E16: Micro-Enterprise / Kirana Reseller | F16: 28 | G16: 15 | H16: 64802.96 | I16: =H16/G16 -> 4320.1973 | J16: Loyal Customers | K16: Multi-Category Cross-Sell Bundle Perks
A17: CUST-0692 | B17: Sanjay Deshmukh | C17: Lucknow | D17: Tier-2 | E17: Micro-Enterprise / Kirana Reseller | F17: 6 | G17: 21 | H17: 62881.08 | I17: =H17/G17 -> 2994.3371 | J17: Champions | K17: VIP Fast-Track SLA & Exclusive Pre-Booking
... A1061: CUST-0420 | B1061: Krishna Pandey | C1061: New Delhi | D1061: Tier-1 | E1061: Retail Consumer | F1061: 61 | G1061: 1 | H1061: 8.55 | I1061: =H1061/G1061 -> 8.55 | J1061: Hibernating / Churned | K1061: Re-Engagement Reactivation Survey & Prune
A1062: Total / Network Customers | F1062: =AVERAGE(F6:F1061) -> 62.598485 | G1062: =SUM(G6:G1061) -> 7867 | H1062: =SUM(H6:H1061) -> 6115289.5 | I1062: =H1062/G1062 -> 777.33438

Sheet Logistics_Hub_Diagnostic
A1: NETWORK FULFILLMENT HUBS & LOGISTICS BOTTLENECK DIAGNOSTIC
A2: Node-Level Lead Time Analysis | SLA Adherence | Stockout-Induced Order Cancellations
A4: Hub ID | B4: Hub Name | C4: Facility Type | D4: City | E4: Tier | F4: Zone | G4: Total Orders | H4: Delivered Orders | I4: SLA Breach % | J4: Stockout Cancel %
A5: HUB-GAU-RDH | B5: Regional Distribution Hub North-East | C5: Regional Hub | D5: Guwahati | E5: Tier-2 | F5: North-East | G5: 940 | H5: 829 | I5: 0.2468 | J5: 0.0521
A6: HUB-DAR-KIR | B6: Hyperlocal Kirana SNP Darbhanga Bazaar | C6: Kirana Network Participant | D6: Darbhanga | E6: Tier-3 | F6: East | G6: 722 | H6: 635 | I6: 0.1787 | J6: 0.0609
A7: HUB-KOL-RDH | B7: Regional Distribution Hub East | C7: Regional Hub | D7: Kolkata | E7: Tier-1 | F7: East | G7: 699 | H7: 626 | I7: 0.2031 | J7: 0.0329
A8: HUB-PAT-RDH | B8: Regional Distribution Hub Magadh | C8: Regional Hub | D8: Patna | E8: Tier-2 | F8: East | G8: 678 | H8: 599 | I8: 0.233 | J8: 0.0531
A9: HUB-BHO-RDH | B9: Regional Distribution Hub Malwa | C9: Regional Hub | D9: Bhopal | E9: Tier-2 | F9: Central | G9: 608 | H9: 564 | I9: 0.2286 | J9: 0.0395
A10: HUB-COI-RDH | B10: Regional Distribution Hub Kongu | C10: Regional Hub | D10: Coimbatore | E10: Tier-2 | F10: South | G10: 588 | H10: 511 | I10: 0.267 | J10: 0.0646
A11: HUB-WAR-KIR | B11: Hyperlocal Kirana SNP Warangal Town | C11: Kirana Network Participant | D11: Warangal | E11: Tier-3 | F11: South | G11: 582 | H11: 508 | I11: 0.1701 | J11: 0.0498
A12: HUB-BLR-MFC | B12: Urban Dark Store ONDC Koramangala | C12: Micro-Fulfillment Center | D12: Bengaluru | E12: Tier-1 | F12: South | G12: 550 | H12: 490 | I12: 0.1582 | J12: 0.0491
A13: HUB-BLR-CWH | B13: Central Warehouse South (BLR) | C13: Central Warehouse | D13: Hosur | E13: Tier-1 | F13: South | G13: 532 | H13: 474 | I13: 0.235 | J13: 0.0526
A14: HUB-LKO-RDH | B14: Regional Distribution Hub Awadh | C14: Regional Hub | D14: Lucknow | E14: Tier-2 | F14: North | G14: 424 | H14: 365 | I14: 0.2594 | J14: 0.0731
A15: HUB-JAI-RDH | B15: Regional Distribution Hub Marwar | C15: Regional Hub | D15: Jaipur | E15: Tier-2 | F15: North | G15: 419 | H15: 377 | I15: 0.2458 | J15: 0.0525
A16: HUB-DEL-MFC | B16: Urban Dark Store ONDC South Delhi | C16: Micro-Fulfillment Center | D16: New Delhi | E16: Tier-1 | F16: North | G16: 407 | H16: 362 | I16: 0.1941 | J16: 0.0516
... A21: HUB-MUM-MFC | B21: Urban Dark Store ONDC Andheri | C21: Micro-Fulfillment Center | D21: Mumbai | E21: Tier-1 | F21: West | G21: 276 | H21: 247 | I21: 0.1522 | J21: 0.0471
A22: Total / Network Benchmark | G22: =SUM(G5:G21) -> 8866 | H22: =SUM(H5:H21) -> 7867 | I22: =AVERAGE(I5:I21) -> 0.21372941 | J22: =AVERAGE(J5:J21) -> 0.051235294

Sheet Assumptions_Data_Model
A1: DATA DICTIONARY, FORMULA ARCHITECTURE & OPERATIONAL ASSUMPTIONS
A2: Project BHARAT-FLOW | ONDC Network Grounding & Methodological Reference
A4: Parameter / Metric | B4: Formula / Standard | C4: Default Value / Threshold | D4: Business Purpose & Context
A5: ABC Analysis (Pareto) | B5: A: <= 80% Cumul. Value, B: 80-95%, C: > 95% | C5: 80% / 15% / 5% Revenue Split | D5: Separates critical high-capital drivers from low-value tail items.
A6: XYZ Demand Volatility | B6: CV = Standard Deviation / Mean Monthly Demand | C6: X: <= 0.45, Y: 0.45-0.85, Z: > 0.85 | D6: Measures predictability to determine make-to-stock vs pull replenishment.
A7: Safety Stock (SS) | B7: SS = Z * SQRT(L*sigma_d^2 + d^2*sigma_L^2) | C7: Z = 1.65 (95% Service Level) | D7: Protects against both consumer demand spikes and supplier transit variance.
A8: Reorder Point (ROP) | B8: ROP = (Daily Demand * Lead Time) + Safety Stock | C8: Dynamic per SKU | D8: Triggers purchase orders before stock falls into dangerous stockout zones.
A9: Economic Order Quantity | B9: EOQ = SQRT((2 * Annual_Demand * Ordering_Cost) / H) | C9: H = Unit_Cost * Holding_Rate | D9: Minimizes combined total of annual ordering costs and carrying costs.
A10: RFM Recency Score | B10: NTILE(5) based on days since last order (to 2026-09-30) | C10: 1 (Cold) to 5 (Ordered within 14d) | D10: Identifies transaction freshness and immediate re-engagement opportunity.
A11: RFM Frequency Score | B11: NTILE(5) based on count of delivered orders | C11: 1 (1-2 orders) to 5 (> 15 orders) | D11: Measures brand loyalty and repeat purchasing habits across ONDC buyer apps.
A12: RFM Monetary Score | B12: NTILE(5) based on cumulative GMV spend in INR | C12: 1 (< ₹1,500) to 5 (> ₹15,000) | D12: Identifies high-value enterprise accounts and high-spending households.
A13: Monsoon Transit Friction | B13: +35% lead time and higher delay variance in July-Aug | C13: 75-80% delivery SLA | D13: Models Indian climate realities on highway networks and last-mile flooding.
A14: Festive Demand Shock | B14: +40% order volume spike during Diwali/Dussehra | C14: October – November peak | D14: Models consumer stocking behavior and pre-festival bulk purchasing.
